MANIFEST.in
README.rst
setup.py
aliyun_python_sdk_httpdns.egg-info/PKG-INFO
aliyun_python_sdk_httpdns.egg-info/SOURCES.txt
aliyun_python_sdk_httpdns.egg-info/dependency_links.txt
aliyun_python_sdk_httpdns.egg-info/requires.txt
aliyun_python_sdk_httpdns.egg-info/top_level.txt
aliyunsdkhttpdns/__init__.py
aliyunsdkhttpdns/request/__init__.py
aliyunsdkhttpdns/request/v20160201/AddDomainRequest.py
aliyunsdkhttpdns/request/v20160201/DeleteDomainRequest.py
aliyunsdkhttpdns/request/v20160201/DescribeDomainsRequest.py
aliyunsdkhttpdns/request/v20160201/GetAccountInfoRequest.py
aliyunsdkhttpdns/request/v20160201/GetResolveCountSummaryRequest.py
aliyunsdkhttpdns/request/v20160201/GetResolveStatisticsRequest.py
aliyunsdkhttpdns/request/v20160201/ListDomainsRequest.py
aliyunsdkhttpdns/request/v20160201/__init__.py